drmaciver_junkdrawer/__init__.py
drmaciver_junkdrawer/coin.py
drmaciver_junkdrawer/guessing.py
drmaciver_junkdrawer/maskedsequence.py
drmaciver_junkdrawer/poprandom.py
drmaciver_junkdrawer/sampler.py
drmaciver_junkdrawer-0.2.0.dist-info/METADATA
drmaciver_junkdrawer-0.2.0.dist-info/WHEEL
drmaciver_junkdrawer-0.2.0.dist-info/licenses/LICENSE
drmaciver_junkdrawer-0.2.0.dist-info/RECORD
