Metadata-Version: 2.3
Name: drmaciver-junkdrawer
Version: 0.2.0
Summary: A collection of miscellaneous tools that DRMacIver finds useful.
License-File: LICENSE
Requires-Python: >=3.12
